spatialleiden/__init__.py
spatialleiden/_multiplex_leiden.py
spatialleiden/_resolution_search.py
spatialleiden/_utils.py
spatialleiden-0.3.0.dist-info/licenses/LICENSE
spatialleiden-0.3.0.dist-info/METADATA
spatialleiden-0.3.0.dist-info/WHEEL
spatialleiden-0.3.0.dist-info/top_level.txt
spatialleiden-0.3.0.dist-info/RECORD
