Metadata-Version: 2.4
Name: spatialleiden
Version: 0.3.0
Summary: Implementation of multiplex Leiden for analysis of (multimodal) spatial omics data.
Author-email: Niklas Müller-Bötticher <niklas.mueller-boetticher@charite.de>, Shashwat Sahay <shashwatsahay.rsg@gmail.com>
License-Expression: MIT
Project-URL: Homepage, https://github.com/HiDiHlabs/SpatialLeiden
Project-URL: Documentation, https://spatialleiden.readthedocs.io
Project-URL: Repository, https://github.com/HiDiHlabs/SpatialLeiden
Project-URL: Issues, https://github.com/HiDiHlabs/SpatialLeiden/issues
Classifier: Intended Audience :: Science/Research
Classifier: Programming Language :: Python
Classifier: Programming Language :: Python :: 3
Classifier: Programming Language :: Python :: 3 :: Only
Classifier: Topic :: Scientific/Engineering
Classifier: Topic :: Scientific/Engineering :: Bio-Informatics
Classifier: Typing :: Typed
Requires-Python: >=3.10
License-File: LICENSE
Requires-Dist: igraph
Requires-Dist: leidenalg~=0.10.2
Requires-Dist: numpy>=1.21
Requires-Dist: scipy>=1.9
Provides-Extra: docs
Requires-Dist: sphinx; extra == "docs"
Requires-Dist: sphinx-copybutton; extra == "docs"
Requires-Dist: sphinx-rtd-theme; extra == "docs"
Requires-Dist: anndata>=0.10; extra == "docs"
Requires-Dist: scanpy; extra == "docs"
Requires-Dist: squidpy; extra == "docs"
Requires-Dist: dask<2025; extra == "docs"
Requires-Dist: myst-nb; extra == "docs"
Provides-Extra: dev
Requires-Dist: spatialleiden[docs]; extra == "dev"
Requires-Dist: mudata~=0.3; extra == "dev"
Requires-Dist: pre-commit; extra == "dev"
Dynamic: license-file
